{
   "conditions": [],
   "description": "The measurement of dimension of an alloy in its form, often ingot",
   "name": "MeasureDimensions",
   "parameters": [],
   "properties": [
      [
         {
            "id": "8e6c0ea5-411d-421b-b98f-db693ca914cb",
            "scope": "auto",
            "type": "link_by_uid"
         },
         null
      ],
      [
         {
            "id": "3656dd21-685a-4018-8817-2e522838e0cf",
            "scope": "auto",
            "type": "link_by_uid"
         },
         null
      ],
      [
         {
            "id": "1df222dd-49b2-4517-bf2c-ea801c923dfa",
            "scope": "auto",
            "type": "link_by_uid"
         },
         null
      ],
      [
         {
            "id": "82eec07e-b90c-497f-be25-12203c5dbc16",
            "scope": "auto",
            "type": "link_by_uid"
         },
         null
      ]
   ],
   "tags": [],
   "type": "measurement_template",
   "uids": {
      "auto": "4d8cea7a-01f8-4ddc-a9ab-561cc0811987",
      "persistent_id": 28
   }
}