{
   "absolute_quantity": null,
   "file_links": [],
   "labels": [],
   "mass_fraction": null,
   "material": {
      "id": "464ccd2f-6353-4298-ae23-b3062078c172",
      "scope": "auto",
      "type": "link_by_uid"
   },
   "name": "Al in AAB08 Ing.",
   "notes": null,
   "number_fraction": null,
   "process": {
      "id": "42a52e61-49a4-4724-aef2-051dc899a3ff",
      "scope": "auto",
      "type": "link_by_uid"
   },
   "tags": [],
   "type": "ingredient_spec",
   "uids": {
      "auto": "a6560fa9-b663-4ce6-9613-1659105bff42"
   },
   "volume_fraction": null
}