{
   "conditions": [],
   "file_links": [],
   "material": {
      "id": "3f76423e-a971-4ac1-a44b-4f6c3a07a41c",
      "scope": "auto",
      "type": "link_by_uid"
   },
   "name": "XRD charact. for Alloy (AAB05-VAM-A) (T03)",
   "notes": null,
   "parameters": [],
   "properties": [
      {
         "file_links": [],
         "name": "Phase",
         "notes": "",
         "origin": "measured",
         "template": null,
         "type": "property",
         "value": {
            "category": "FCC",
            "type": "nominal_categorical"
         }
      },
      {
         "file_links": [],
         "name": "Lattice Parameter",
         "notes": "",
         "origin": "measured",
         "template": null,
         "type": "property",
         "value": {
            "nominal": 3.571466348781675,
            "type": "nominal_real",
            "units": "centimeter"
         }
      },
      {
         "file_links": [],
         "name": "Hardness, HV",
         "notes": "",
         "origin": "measured",
         "template": null,
         "type": "property",
         "value": {
            "nominal": 200.29999999999998,
            "type": "nominal_real",
            "units": "pascal"
         }
      },
      {
         "file_links": [],
         "name": "SD, HV",
         "notes": "",
         "origin": "measured",
         "template": null,
         "type": "property",
         "value": {
            "nominal": 6.764244229771717,
            "type": "nominal_real",
            "units": "pascal"
         }
      }
   ],
   "source": null,
   "spec": {
      "id": "460f68a9-9f6f-4d29-b70a-5589455813f3",
      "scope": "auto",
      "type": "link_by_uid"
   },
   "tags": [
      "composition_id::AAB05",
      "batch::A",
      "fabrication_method::VAM"
   ],
   "type": "measurement_run",
   "uids": {
      "auto": "0d3742f8-7dc7-4182-9c77-1e90bf39da27"
   }
}