{
   "absolute_quantity": null,
   "file_links": [],
   "labels": [],
   "mass_fraction": null,
   "material": {
      "id": "56b67691-c62b-4b10-8bc0-452e860c6778",
      "scope": "auto",
      "type": "link_by_uid"
   },
   "name": "Composition AAB03 Ing.",
   "notes": null,
   "number_fraction": null,
   "process": {
      "id": "85f37205-52d8-4997-8c0a-81497545b253",
      "scope": "auto",
      "type": "link_by_uid"
   },
   "tags": [],
   "type": "ingredient_spec",
   "uids": {
      "auto": "5b3b47ae-7d9c-4d0b-a026-c05b0bb6b2f7"
   },
   "volume_fraction": null
}