{
   "absolute_quantity": null,
   "file_links": [],
   "labels": [],
   "mass_fraction": null,
   "material": {
      "id": "03a37a46-b254-4563-b380-8a97624f0257",
      "scope": "auto",
      "type": "link_by_uid"
   },
   "name": "Composition AAB07 Ing.",
   "notes": null,
   "number_fraction": null,
   "process": {
      "id": "fff806e8-1cc6-47fc-9715-b0d5df647728",
      "scope": "auto",
      "type": "link_by_uid"
   },
   "tags": [],
   "type": "ingredient_spec",
   "uids": {
      "auto": "1c8e6e8e-aa1e-4eb8-bcf2-f7917b3b4bf4"
   },
   "volume_fraction": null
}