{
   "absolute_quantity": null,
   "file_links": [],
   "labels": [],
   "mass_fraction": null,
   "material": {
      "id": "59d024fe-9387-4a56-a272-259ac51c2e44",
      "scope": "auto",
      "type": "link_by_uid"
   },
   "name": "Composition AAB15 Ing.",
   "notes": null,
   "number_fraction": null,
   "process": {
      "id": "04afa706-e6cc-4e1a-ba36-895e535c32b0",
      "scope": "auto",
      "type": "link_by_uid"
   },
   "spec": {
      "id": "274d1195-69e1-4bd8-ac2b-54f2cbecd0f9",
      "scope": "auto",
      "type": "link_by_uid"
   },
   "tags": [],
   "type": "ingredient_run",
   "uids": {
      "auto": "3c9b38a3-92fd-48e7-980d-84f7934ed269"
   },
   "volume_fraction": null
}