{
   "conditions": [],
   "file_links": [],
   "material": {
      "id": "020ea51b-e513-48d8-ad05-745210adcf9a",
      "scope": "auto",
      "type": "link_by_uid"
   },
   "name": "SEM charact. for Alloy (AAB15-VAM-A) (T02)",
   "notes": null,
   "parameters": [],
   "properties": [],
   "source": null,
   "spec": {
      "id": "b37d716e-7d13-4c57-85e4-f6172fdc224f",
      "scope": "auto",
      "type": "link_by_uid"
   },
   "tags": [
      "composition_id::AAB15",
      "batch::A",
      "fabrication_method::VAM"
   ],
   "type": "measurement_run",
   "uids": {
      "auto": "53db853a-526d-4945-860b-8ab8825337c9"
   }
}