{
   "absolute_quantity": null,
   "file_links": [],
   "labels": [],
   "mass_fraction": null,
   "material": {
      "id": "de3d85a6-c6df-4b83-ac08-141be8f890d2",
      "scope": "auto",
      "type": "link_by_uid"
   },
   "name": "Composition AAB12 Ing.",
   "notes": null,
   "number_fraction": null,
   "process": {
      "id": "b04486d5-cb6e-4e8a-9382-1a4c7ab2635d",
      "scope": "auto",
      "type": "link_by_uid"
   },
   "tags": [],
   "type": "ingredient_spec",
   "uids": {
      "auto": "e6a0f1d1-fa3e-45d9-a289-2245d886be96"
   },
   "volume_fraction": null
}