{
   "absolute_quantity": null,
   "file_links": [],
   "labels": [],
   "mass_fraction": null,
   "material": {
      "id": "fc55bc3e-000a-4103-9f13-ee65f75b7413",
      "scope": "auto",
      "type": "link_by_uid"
   },
   "name": "Composition AAB03 Ing.",
   "notes": null,
   "number_fraction": null,
   "process": {
      "id": "7effa601-3808-42e0-a5bc-21d00702b090",
      "scope": "auto",
      "type": "link_by_uid"
   },
   "spec": {
      "id": "169cfa13-4fc3-4894-922b-726d3b9860fa",
      "scope": "auto",
      "type": "link_by_uid"
   },
   "tags": [],
   "type": "ingredient_run",
   "uids": {
      "auto": "d9c88c40-c28a-4953-8665-dcb82479b8ef"
   },
   "volume_fraction": null
}