{
   "absolute_quantity": null,
   "file_links": [],
   "labels": [],
   "mass_fraction": null,
   "material": {
      "id": "80dc75c8-3059-43c0-8840-df8464cbe103",
      "scope": "auto",
      "type": "link_by_uid"
   },
   "name": "Al in AAB07 Ing.",
   "notes": null,
   "number_fraction": null,
   "process": {
      "id": "915d0eea-00c0-4647-baa0-ea85576dafd6",
      "scope": "auto",
      "type": "link_by_uid"
   },
   "tags": [],
   "type": "ingredient_spec",
   "uids": {
      "auto": "78521f35-3edc-4890-a153-67f31f21453a"
   },
   "volume_fraction": null
}