{
   "absolute_quantity": null,
   "file_links": [],
   "labels": [],
   "mass_fraction": null,
   "material": {
      "id": "4401d7d1-57c1-410f-ad9e-d9db564f9724",
      "scope": "auto",
      "type": "link_by_uid"
   },
   "name": "Composition AAB06 Ing.",
   "notes": null,
   "number_fraction": null,
   "process": {
      "id": "c172013d-f859-401f-a684-735ed7d36c40",
      "scope": "auto",
      "type": "link_by_uid"
   },
   "tags": [],
   "type": "ingredient_spec",
   "uids": {
      "auto": "2a73b6be-b074-4172-954a-0eb1d824e47d"
   },
   "volume_fraction": null
}