{
   "absolute_quantity": null,
   "file_links": [],
   "labels": [],
   "mass_fraction": null,
   "material": {
      "id": "eac9e2a9-5180-4446-9564-5400c99fd565",
      "scope": "auto",
      "type": "link_by_uid"
   },
   "name": "Inferred Alloy Compositions Ing.",
   "notes": null,
   "number_fraction": null,
   "process": {
      "id": "a6ac52ff-5ebf-42c1-ad70-5011bc3e3ad2",
      "scope": "auto",
      "type": "link_by_uid"
   },
   "spec": {
      "id": "87bca68d-bc9b-4935-bc83-b480b72d17b7",
      "scope": "auto",
      "type": "link_by_uid"
   },
   "tags": [],
   "type": "ingredient_run",
   "uids": {
      "auto": "f9d4064a-df4a-4543-8513-02a1a240f530"
   },
   "volume_fraction": null
}