{
   "absolute_quantity": null,
   "file_links": [],
   "labels": [],
   "mass_fraction": null,
   "material": {
      "id": "8b5a6d1f-b956-4f72-974b-4fb5ab05b5a4",
      "scope": "auto",
      "type": "link_by_uid"
   },
   "name": "Al in AAB11 Ing.",
   "notes": null,
   "number_fraction": null,
   "process": {
      "id": "c8e8fe76-759c-4bb2-9e08-a5ab4a111400",
      "scope": "auto",
      "type": "link_by_uid"
   },
   "spec": {
      "id": "e411d177-1980-48ec-90c6-9c2d6924bd5c",
      "scope": "auto",
      "type": "link_by_uid"
   },
   "tags": [],
   "type": "ingredient_run",
   "uids": {
      "auto": "6382f7d7-fac8-4861-9054-760e0e7ebe43"
   },
   "volume_fraction": null
}