{
   "absolute_quantity": null,
   "file_links": [],
   "labels": [],
   "mass_fraction": null,
   "material": {
      "id": "31a3aded-fe49-4fd8-9a1e-7c6eb2291942",
      "scope": "auto",
      "type": "link_by_uid"
   },
   "name": "Alloy (AAB01-VAM-A): T. Sample (NI, T04) Ing.",
   "notes": null,
   "number_fraction": null,
   "process": {
      "id": "f91e7d82-39f4-494c-a5d6-3e8a1ebc179d",
      "scope": "auto",
      "type": "link_by_uid"
   },
   "tags": [],
   "type": "ingredient_spec",
   "uids": {
      "auto": "fb766466-46b3-4534-a6b4-af6e7121b64c"
   },
   "volume_fraction": null
}