{
   "file_links": [],
   "name": "Fe in AAB12",
   "notes": null,
   "process": {
      "id": "45c93b7c-7833-4c86-95df-c1d0feafe0cb",
      "scope": "auto",
      "type": "link_by_uid"
   },
   "properties": [
      {
         "conditions": [],
         "property": {
            "file_links": [],
            "name": "Composition Percentage",
            "notes": "",
            "origin": "predicted",
            "template": null,
            "type": "property",
            "value": {
               "nominal": 20.0,
               "type": "nominal_real",
               "units": "dimensionless"
            }
         },
         "type": "property_and_conditions"
      },
      {
         "conditions": [],
         "property": {
            "file_links": [],
            "name": "Target Mass",
            "notes": "",
            "origin": "computed",
            "template": null,
            "type": "property",
            "value": {
               "nominal": 5.9542,
               "type": "nominal_real",
               "units": "gram"
            }
         },
         "type": "property_and_conditions"
      }
   ],
   "tags": [],
   "template": {
      "id": "70b30b0f-776a-4170-be9b-0962be16b96f",
      "scope": "auto",
      "type": "link_by_uid"
   },
   "type": "material_spec",
   "uids": {
      "auto": "e02f8ac1-8801-48f0-8f4e-287c759f154d"
   }
}