{
   "absolute_quantity": null,
   "file_links": [],
   "labels": [],
   "mass_fraction": null,
   "material": {
      "id": "320a2cf6-6481-4454-8b1f-cc59ea2aae04",
      "scope": "auto",
      "type": "link_by_uid"
   },
   "name": "Cr in AAB04 Ing.",
   "notes": null,
   "number_fraction": null,
   "process": {
      "id": "2dadbb0f-e65f-4003-beda-b48628afd59f",
      "scope": "auto",
      "type": "link_by_uid"
   },
   "tags": [],
   "type": "ingredient_spec",
   "uids": {
      "auto": "56f8e4c8-19cd-40bc-8ed4-8676fb8bb207"
   },
   "volume_fraction": null
}