{
   "file_links": [],
   "name": "V in AAB10",
   "notes": null,
   "process": {
      "id": "6ddc5b9b-6b9d-42d3-8a67-0a45e36cee82",
      "scope": "auto",
      "type": "link_by_uid"
   },
   "properties": [
      {
         "conditions": [],
         "property": {
            "file_links": [],
            "name": "Composition Percentage",
            "notes": "",
            "origin": "predicted",
            "template": null,
            "type": "property",
            "value": {
               "nominal": 0.0,
               "type": "nominal_real",
               "units": "dimensionless"
            }
         },
         "type": "property_and_conditions"
      },
      {
         "conditions": [],
         "property": {
            "file_links": [],
            "name": "Target Mass",
            "notes": "",
            "origin": "computed",
            "template": null,
            "type": "property",
            "value": {
               "nominal": 0.0,
               "type": "nominal_real",
               "units": "gram"
            }
         },
         "type": "property_and_conditions"
      }
   ],
   "tags": [],
   "template": {
      "id": "d4f61de0-ba41-4cbe-8fbb-3eac00aa4ede",
      "scope": "auto",
      "type": "link_by_uid"
   },
   "type": "material_spec",
   "uids": {
      "auto": "f6c6aa5f-0de6-448a-9887-9f2fc4dfde7c"
   }
}