{
   "absolute_quantity": null,
   "file_links": [],
   "labels": [],
   "mass_fraction": null,
   "material": {
      "id": "f7254b91-c6fd-4466-8000-bf4d70883ca0",
      "scope": "auto",
      "type": "link_by_uid"
   },
   "name": "Ni in AAB12 Ing.",
   "notes": null,
   "number_fraction": null,
   "process": {
      "id": "4c9b7c85-869c-4a6f-af15-ee3489a39961",
      "scope": "auto",
      "type": "link_by_uid"
   },
   "spec": {
      "id": "303de344-8bf9-4497-ab74-6faa8600b3f3",
      "scope": "auto",
      "type": "link_by_uid"
   },
   "tags": [],
   "type": "ingredient_run",
   "uids": {
      "auto": "202d39d1-0c3e-4ded-a727-357e01bf2833"
   },
   "volume_fraction": null
}