{
   "absolute_quantity": null,
   "file_links": [],
   "labels": [],
   "mass_fraction": null,
   "material": {
      "id": "85e3f49b-27bb-457f-b249-3fa394906ea1",
      "scope": "auto",
      "type": "link_by_uid"
   },
   "name": "Alloy (AAB07-VAM-A) Ing.",
   "notes": null,
   "number_fraction": null,
   "process": {
      "id": "fbd34199-9e59-447a-817a-e18476cc4d1a",
      "scope": "auto",
      "type": "link_by_uid"
   },
   "spec": {
      "id": "338216e2-1520-4cf0-b984-8a65c344a781",
      "scope": "auto",
      "type": "link_by_uid"
   },
   "tags": [],
   "type": "ingredient_run",
   "uids": {
      "auto": "89438cb0-ea09-46da-aa99-99c5b4a96246"
   },
   "volume_fraction": null
}