{
   "absolute_quantity": null,
   "file_links": [],
   "labels": [],
   "mass_fraction": null,
   "material": {
      "id": "24ecf866-8393-4059-9728-5823843553ab",
      "scope": "auto",
      "type": "link_by_uid"
   },
   "name": "Arc Melted Alloy (AAB11-VAM-A) Ing.",
   "notes": null,
   "number_fraction": null,
   "process": {
      "id": "424fcfce-25ee-4ee8-8f48-9dc6a6b2a060",
      "scope": "auto",
      "type": "link_by_uid"
   },
   "spec": {
      "id": "f4f31cdf-8aa1-4863-8bc4-af0bdedf024c",
      "scope": "auto",
      "type": "link_by_uid"
   },
   "tags": [],
   "type": "ingredient_run",
   "uids": {
      "auto": "9146c43d-9733-4d13-b6b8-965c3469dc2c"
   },
   "volume_fraction": null
}