{
   "absolute_quantity": null,
   "file_links": [],
   "labels": [],
   "mass_fraction": null,
   "material": {
      "id": "9b89c4dc-a061-42f5-8189-6d538af19b36",
      "scope": "auto",
      "type": "link_by_uid"
   },
   "name": "Alloy (AAB13-VAM-A): T. Sample (NI, T04) Ing.",
   "notes": null,
   "number_fraction": null,
   "process": {
      "id": "f48beb5c-8f52-461a-867e-5833c37ffd75",
      "scope": "auto",
      "type": "link_by_uid"
   },
   "tags": [],
   "type": "ingredient_spec",
   "uids": {
      "auto": "81b9e69f-d2dd-40a9-a6d3-323367ff566f"
   },
   "volume_fraction": null
}