{
   "absolute_quantity": null,
   "file_links": [],
   "labels": [],
   "mass_fraction": null,
   "material": {
      "id": "26847dce-7081-4ddf-8f56-c2f8a28e0316",
      "scope": "auto",
      "type": "link_by_uid"
   },
   "name": "Arc Melted Alloy (AAB12-VAM-A) Ing.",
   "notes": null,
   "number_fraction": null,
   "process": {
      "id": "5899743e-3e0e-4575-b6e3-0071c180ef86",
      "scope": "auto",
      "type": "link_by_uid"
   },
   "spec": {
      "id": "70451892-2999-47c6-b6dd-a5b759018588",
      "scope": "auto",
      "type": "link_by_uid"
   },
   "tags": [],
   "type": "ingredient_run",
   "uids": {
      "auto": "11a3b6a1-f741-4fff-8125-e9621d97160d"
   },
   "volume_fraction": null
}