{
   "absolute_quantity": null,
   "file_links": [],
   "labels": [],
   "mass_fraction": null,
   "material": {
      "id": "b12d680f-45f3-4c80-ac72-da4d2da7802e",
      "scope": "auto",
      "type": "link_by_uid"
   },
   "name": "Alloy (AAB16-VAM-A): T. Sample (NI, T04) Ing.",
   "notes": null,
   "number_fraction": null,
   "process": {
      "id": "d45e4d99-f998-434a-b612-2a76dbb687c1",
      "scope": "auto",
      "type": "link_by_uid"
   },
   "spec": {
      "id": "bb5eb222-0380-4920-a1aa-48f5f8bf3e7c",
      "scope": "auto",
      "type": "link_by_uid"
   },
   "tags": [],
   "type": "ingredient_run",
   "uids": {
      "auto": "ef73665e-2d0a-4bf3-82f1-7f3347d0716c"
   },
   "volume_fraction": null
}