{
   "absolute_quantity": null,
   "file_links": [],
   "labels": [],
   "mass_fraction": null,
   "material": {
      "id": "7e270554-35f9-4580-8041-c3770b38abe7",
      "scope": "auto",
      "type": "link_by_uid"
   },
   "name": "Alloy (AAB07-VAM-A): T. Sample (SEM, T02) Ing.",
   "notes": null,
   "number_fraction": null,
   "process": {
      "id": "cc7bc8bf-2f54-48e0-851a-6dea97f23dbf",
      "scope": "auto",
      "type": "link_by_uid"
   },
   "spec": {
      "id": "01a1a82c-6566-46fd-b61b-61bc0c48cbb2",
      "scope": "auto",
      "type": "link_by_uid"
   },
   "tags": [],
   "type": "ingredient_run",
   "uids": {
      "auto": "4685fc7c-84bf-44a6-98a0-7b17b374075c"
   },
   "volume_fraction": null
}