{
   "absolute_quantity": null,
   "file_links": [],
   "labels": [],
   "mass_fraction": null,
   "material": {
      "id": "a80a3509-b9bf-4d19-b8be-6f3415d3b1cf",
      "scope": "auto",
      "type": "link_by_uid"
   },
   "name": "Alloy (AAB15-VAM-A): Traveler Ing.",
   "notes": null,
   "number_fraction": null,
   "process": {
      "id": "5c99f5d3-b532-49f8-bc1b-d9edba4f1784",
      "scope": "auto",
      "type": "link_by_uid"
   },
   "spec": {
      "id": "4ed168f0-9460-45d5-a56d-609c32cf3a9f",
      "scope": "auto",
      "type": "link_by_uid"
   },
   "tags": [],
   "type": "ingredient_run",
   "uids": {
      "auto": "5346d8bd-e18a-4078-98d8-9fda8c412f67"
   },
   "volume_fraction": null
}