{
   "absolute_quantity": null,
   "file_links": [],
   "labels": [],
   "mass_fraction": null,
   "material": {
      "id": "3507c0a9-2dc0-45c3-bed5-43c7fa182406",
      "scope": "auto",
      "type": "link_by_uid"
   },
   "name": "V in AAB12 Ing.",
   "notes": null,
   "number_fraction": null,
   "process": {
      "id": "332c9f3b-3f4a-4b55-b9d9-c1be4191e7e2",
      "scope": "auto",
      "type": "link_by_uid"
   },
   "spec": {
      "id": "0262fef3-ae8e-4d3f-8c20-1e3df3e82321",
      "scope": "auto",
      "type": "link_by_uid"
   },
   "tags": [],
   "type": "ingredient_run",
   "uids": {
      "auto": "87d8e6da-bccc-41f7-a6aa-626070d8723a"
   },
   "volume_fraction": null
}