{
   "absolute_quantity": null,
   "file_links": [],
   "labels": [],
   "mass_fraction": null,
   "material": {
      "id": "e262cab0-2473-4445-8a08-37de680e5926",
      "scope": "auto",
      "type": "link_by_uid"
   },
   "name": "Composition AAB02 Ing.",
   "notes": null,
   "number_fraction": null,
   "process": {
      "id": "f944a04f-bfeb-4b76-8dfb-129aa25e9866",
      "scope": "auto",
      "type": "link_by_uid"
   },
   "tags": [],
   "type": "ingredient_spec",
   "uids": {
      "auto": "0daa20e4-9a48-42d7-b147-0a658c4e11d7"
   },
   "volume_fraction": null
}