{
   "absolute_quantity": null,
   "file_links": [],
   "labels": [],
   "mass_fraction": null,
   "material": {
      "id": "cefc67f3-63c6-4014-8850-6ecde31aa2af",
      "scope": "auto",
      "type": "link_by_uid"
   },
   "name": "Alloy (AAB05-VAM-A): Traveler Ing.",
   "notes": null,
   "number_fraction": null,
   "process": {
      "id": "a9bba4b1-e7c9-4b27-b57a-5d1aec24178f",
      "scope": "auto",
      "type": "link_by_uid"
   },
   "tags": [],
   "type": "ingredient_spec",
   "uids": {
      "auto": "bff17ebc-e19d-45d8-8980-fd7f988f1af0"
   },
   "volume_fraction": null
}