{
   "absolute_quantity": null,
   "file_links": [],
   "labels": [],
   "mass_fraction": null,
   "material": {
      "id": "e36bcb12-4091-4558-b265-8423c4060c4a",
      "scope": "auto",
      "type": "link_by_uid"
   },
   "name": "Alloy (AAB03-VAM-A): Traveler Ing.",
   "notes": null,
   "number_fraction": null,
   "process": {
      "id": "1e7301c6-c4cb-47f0-a501-a6afd10c5624",
      "scope": "auto",
      "type": "link_by_uid"
   },
   "tags": [],
   "type": "ingredient_spec",
   "uids": {
      "auto": "7f323959-15f1-43d2-9ba6-ac61a3452c0b"
   },
   "volume_fraction": null
}