{
   "absolute_quantity": null,
   "file_links": [],
   "labels": [],
   "mass_fraction": null,
   "material": {
      "id": "5fdc70ef-586a-49aa-ad0f-73611630cc51",
      "scope": "auto",
      "type": "link_by_uid"
   },
   "name": "Cr in AAB09 Ing.",
   "notes": null,
   "number_fraction": null,
   "process": {
      "id": "5f3bc2bc-9771-42a8-846c-4de77d37b9a1",
      "scope": "auto",
      "type": "link_by_uid"
   },
   "tags": [],
   "type": "ingredient_spec",
   "uids": {
      "auto": "f3354bf0-f8c6-4141-82d0-fbac06eec5d2"
   },
   "volume_fraction": null
}