{
   "absolute_quantity": null,
   "file_links": [],
   "labels": [],
   "mass_fraction": null,
   "material": {
      "id": "ea24e222-40a9-47f7-b169-de67852ae077",
      "scope": "auto",
      "type": "link_by_uid"
   },
   "name": "Co in AAB01 Ing.",
   "notes": null,
   "number_fraction": null,
   "process": {
      "id": "24c1bcc1-bc10-42b9-bc70-b554132fb56f",
      "scope": "auto",
      "type": "link_by_uid"
   },
   "tags": [],
   "type": "ingredient_spec",
   "uids": {
      "auto": "37141a5c-ab1e-4b89-91a5-f1d3893d119e"
   },
   "volume_fraction": null
}