{
   "file_links": [],
   "name": "Alloy (AAB02-VAM-A): T. Sample (SEM, T02)",
   "notes": null,
   "process": {
      "id": "970e8b0a-c4b5-45e7-b517-ab60c1576790",
      "scope": "auto",
      "type": "link_by_uid"
   },
   "sample_type": null,
   "spec": {
      "id": "79711f22-15e1-4811-b046-d128d8109d2c",
      "scope": "auto",
      "type": "link_by_uid"
   },
   "tags": [
      "composition_id::AAB02",
      "batch::A",
      "fabrication_method::VAM"
   ],
   "type": "material_run",
   "uids": {
      "auto": "c70a94d2-1181-44ab-be2f-357dee6b60da"
   }
}