{
   "file_links": [],
   "name": "Co in AAB16",
   "notes": null,
   "process": {
      "id": "fb5474e2-7c66-48c4-95e5-fe7040321adc",
      "scope": "auto",
      "type": "link_by_uid"
   },
   "sample_type": "production",
   "spec": {
      "id": "2b731c39-d138-486e-9888-3636671d99b7",
      "scope": "auto",
      "type": "link_by_uid"
   },
   "tags": [
      "composition_id::AAB16",
      "batch::A",
      "fabrication_method::VAM"
   ],
   "type": "material_run",
   "uids": {
      "auto": "7fbd2f4c-510a-4700-bee3-ed00c872f4d1"
   }
}