{
   "file_links": [],
   "name": "Homogenized Alloy (AAB01-VAM-A)",
   "notes": null,
   "process": {
      "id": "5a0c406d-8e0f-4e98-a3b8-0c6d39ab3dc7",
      "scope": "auto",
      "type": "link_by_uid"
   },
   "properties": [
      {
         "conditions": [],
         "property": {
            "file_links": [],
            "name": "Form",
            "notes": "",
            "origin": "predicted",
            "template": null,
            "type": "property",
            "value": {
               "category": "Ingot",
               "type": "nominal_categorical"
            }
         },
         "type": "property_and_conditions"
      }
   ],
   "tags": [],
   "template": {
      "id": "0f81c638-6b73-414a-aba9-08357079e33b",
      "scope": "auto",
      "type": "link_by_uid"
   },
   "type": "material_spec",
   "uids": {
      "auto": "0af8df7c-d596-4073-8a63-8a0f710dc62f"
   }
}