{
   "conditions": [],
   "file_links": [],
   "material": {
      "id": "a27845d0-b32e-49cd-8f64-f77c4a94a7d8",
      "scope": "auto",
      "type": "link_by_uid"
   },
   "name": "Weigh Co for AAB15",
   "notes": null,
   "parameters": [],
   "properties": [
      {
         "file_links": [],
         "name": "Weighed Mass",
         "notes": null,
         "origin": "unknown",
         "template": null,
         "type": "property",
         "value": {
            "nominal": 1.5917,
            "type": "nominal_real",
            "units": "gram"
         }
      },
      {
         "file_links": [],
         "name": "Mass Loss",
         "notes": null,
         "origin": "specified",
         "template": {
            "id": "7a9a713e-727c-4767-9016-a948c723350d",
            "scope": "auto",
            "type": "link_by_uid"
         },
         "type": "property",
         "value": {
            "nominal": 0.0,
            "type": "nominal_real",
            "units": "gram"
         }
      }
   ],
   "source": {
      "performed_by": "Wenle & Daniel",
      "performed_date": "2022-11-04",
      "type": "performed_source"
   },
   "spec": {
      "id": "837dc299-f7dd-457b-ac0b-2264b9d1aec4",
      "scope": "auto",
      "type": "link_by_uid"
   },
   "tags": [
      "composition_id::AAB15",
      "batch::A",
      "fabrication_method::VAM"
   ],
   "type": "measurement_run",
   "uids": {
      "auto": "7e3bcaae-8482-426e-b24b-19ad5e8f1f9e"
   }
}