{
   "conditions": [],
   "file_links": [],
   "material": {
      "id": "8d32b16c-2ba0-47b7-ad86-9620094a6252",
      "scope": "auto",
      "type": "link_by_uid"
   },
   "name": "NI charact. for Alloy (AAB08-VAM-A) (T04)",
   "notes": null,
   "parameters": [],
   "properties": [],
   "source": null,
   "spec": {
      "id": "1ccb8f77-ad49-465e-bb8f-47decc363cf1",
      "scope": "auto",
      "type": "link_by_uid"
   },
   "tags": [
      "composition_id::AAB08",
      "batch::A",
      "fabrication_method::VAM"
   ],
   "type": "measurement_run",
   "uids": {
      "auto": "c2863a2b-f14e-4eb9-97c3-e4436f91f559"
   }
}