{
   "conditions": [],
   "file_links": [],
   "material": {
      "id": "f5d8555f-5bd0-4496-b8c0-4a49962ebf2d",
      "scope": "auto",
      "type": "link_by_uid"
   },
   "name": "SRJT charact. for AAB01",
   "notes": null,
   "parameters": [],
   "properties": [
      {
         "file_links": [],
         "name": "Strain Rate Sensitivity Exponent",
         "notes": "",
         "origin": "measured",
         "template": null,
         "type": "property",
         "value": {
            "nominal": 0.0083582225418888,
            "type": "nominal_real",
            "units": "dimensionless"
         }
      },
      {
         "file_links": [],
         "name": "Strain Rate Sensitivity Exponent Std. Dev.",
         "notes": "",
         "origin": "measured",
         "template": null,
         "type": "property",
         "value": {
            "nominal": 0.0014108980951666,
            "type": "nominal_real",
            "units": "dimensionless"
         }
      },
      {
         "file_links": [],
         "name": "Avg. Raw Hardness (Gpa)",
         "notes": "",
         "origin": "measured",
         "template": null,
         "type": "property",
         "value": {
            "nominal": 2.94,
            "type": "nominal_real",
            "units": "gigapascal"
         }
      },
      {
         "file_links": [],
         "name": "Avg. Raw Modulus (Gpa)",
         "notes": "",
         "origin": "measured",
         "template": null,
         "type": "property",
         "value": {
            "nominal": 213.155555555556,
            "type": "nominal_real",
            "units": "gigapascal"
         }
      },
      {
         "file_links": [],
         "name": "Avg. Pile-up Ratio",
         "notes": "",
         "origin": "measured",
         "template": null,
         "type": "property",
         "value": {
            "nominal": 91.1395333333333,
            "type": "nominal_real",
            "units": "dimensionless"
         }
      },
      {
         "file_links": [],
         "name": "Avg. Corrected Hardness (Gpa)",
         "notes": "",
         "origin": "measured",
         "template": null,
         "type": "property",
         "value": {
            "nominal": 2.67949162111111,
            "type": "nominal_real",
            "units": "gigapascal"
         }
      },
      {
         "file_links": [],
         "name": "Avg. Corrected Modulus (Gpa)",
         "notes": "",
         "origin": "measured",
         "template": null,
         "type": "property",
         "value": {
            "nominal": 194.270378133333,
            "type": "nominal_real",
            "units": "gigapascal"
         }
      }
   ],
   "source": null,
   "spec": {
      "id": "1af8384a-e880-4308-bd17-1537fe69e9a5",
      "scope": "auto",
      "type": "link_by_uid"
   },
   "tags": [
      "composition_id::AAB01",
      "batch::A",
      "fabrication_method::VAM"
   ],
   "type": "measurement_run",
   "uids": {
      "auto": "d9b95c23-a943-4e50-b6f3-1e2935e0f75a"
   }
}