{
   "conditions": [],
   "file_links": [],
   "material": {
      "id": "022dbdf2-ed2d-4324-949f-8f0e1fa62017",
      "scope": "auto",
      "type": "link_by_uid"
   },
   "name": "Weigh Ni for AAB06",
   "notes": null,
   "parameters": [],
   "properties": [
      {
         "file_links": [],
         "name": "Weighed Mass",
         "notes": null,
         "origin": "unknown",
         "template": null,
         "type": "property",
         "value": {
            "nominal": 12.3821,
            "type": "nominal_real",
            "units": "gram"
         }
      },
      {
         "file_links": [],
         "name": "Mass Loss",
         "notes": null,
         "origin": "specified",
         "template": {
            "id": "3ff37629-2103-48e3-8dbb-365421e0ed08",
            "scope": "auto",
            "type": "link_by_uid"
         },
         "type": "property",
         "value": {
            "nominal": 0.0,
            "type": "nominal_real",
            "units": "gram"
         }
      }
   ],
   "source": {
      "performed_by": "Wenle & Daniel",
      "performed_date": "2022-11-04",
      "type": "performed_source"
   },
   "spec": {
      "id": "df559e49-24f3-4b64-966d-ada0bee1dc0b",
      "scope": "auto",
      "type": "link_by_uid"
   },
   "tags": [
      "composition_id::AAB06",
      "batch::A",
      "fabrication_method::VAM"
   ],
   "type": "measurement_run",
   "uids": {
      "auto": "ab40b2bd-145b-4e5a-92bd-07ff76735bb2"
   }
}