{
   "conditions": [],
   "file_links": [],
   "material": {
      "id": "d039ed01-90b4-4cbe-a554-3aad1a9bde88",
      "scope": "auto",
      "type": "link_by_uid"
   },
   "name": "Weigh Arc Melted Alloy (AAB16-VAM-A)",
   "notes": null,
   "parameters": [],
   "properties": [
      {
         "file_links": [],
         "name": "Weighed Mass",
         "notes": null,
         "origin": "unknown",
         "template": null,
         "type": "property",
         "value": {
            "nominal": 29.9817,
            "type": "nominal_real",
            "units": "gram"
         }
      },
      {
         "file_links": [],
         "name": "Mass Loss",
         "notes": null,
         "origin": "unknown",
         "template": null,
         "type": "property",
         "value": {
            "nominal": 0.05,
            "type": "nominal_real",
            "units": "gram"
         }
      }
   ],
   "source": {
      "performed_by": "Daniel",
      "performed_date": "2022-11-05",
      "type": "performed_source"
   },
   "spec": {
      "id": "7d903f33-a24b-43dd-a4ba-7f79d836b479",
      "scope": "auto",
      "type": "link_by_uid"
   },
   "tags": [
      "composition_id::AAB16",
      "batch::A",
      "fabrication_method::VAM"
   ],
   "type": "measurement_run",
   "uids": {
      "auto": "98cf2cc0-e2de-4810-b2d2-a7a2f27f387a"
   }
}