{
   "absolute_quantity": null,
   "file_links": [],
   "labels": [],
   "mass_fraction": null,
   "material": {
      "id": "d0affa74-7f8b-4d26-892e-179057514564",
      "scope": "auto",
      "type": "link_by_uid"
   },
   "name": "Homogenized Alloy (AAB09-VAM-A) Ing.",
   "notes": null,
   "number_fraction": null,
   "process": {
      "id": "23877685-1396-4739-9364-2b74e14f4900",
      "scope": "auto",
      "type": "link_by_uid"
   },
   "spec": {
      "id": "1747d1c7-7d16-4826-9b99-511d307055aa",
      "scope": "auto",
      "type": "link_by_uid"
   },
   "tags": [],
   "type": "ingredient_run",
   "uids": {
      "auto": "6fd217cc-c0ac-45d1-ad21-ac7af55032d3"
   },
   "volume_fraction": null
}