{
   "absolute_quantity": null,
   "file_links": [],
   "labels": [],
   "mass_fraction": null,
   "material": {
      "id": "86df7dcf-057a-4edb-ad16-9e7fb52ad491",
      "scope": "auto",
      "type": "link_by_uid"
   },
   "name": "Composition AAB11 Ing.",
   "notes": null,
   "number_fraction": null,
   "process": {
      "id": "1688018b-c1e7-4d8a-97a8-052625d05090",
      "scope": "auto",
      "type": "link_by_uid"
   },
   "spec": {
      "id": "5cc2f49d-92ea-42fe-990d-7a2b602e0bd3",
      "scope": "auto",
      "type": "link_by_uid"
   },
   "tags": [],
   "type": "ingredient_run",
   "uids": {
      "auto": "075f911d-20ea-49c8-9967-72a64dadc588"
   },
   "volume_fraction": null
}