{
   "absolute_quantity": null,
   "file_links": [],
   "labels": [],
   "mass_fraction": null,
   "material": {
      "id": "e5eeccae-d21e-4816-9bc0-24f43078bca9",
      "scope": "auto",
      "type": "link_by_uid"
   },
   "name": "Alloy (AAB06-VAM-A): Traveler Ing.",
   "notes": null,
   "number_fraction": null,
   "process": {
      "id": "0a274da0-cfa0-4eb4-9773-f6259860580a",
      "scope": "auto",
      "type": "link_by_uid"
   },
   "spec": {
      "id": "000675fe-65e6-40df-9416-05642b73a905",
      "scope": "auto",
      "type": "link_by_uid"
   },
   "tags": [],
   "type": "ingredient_run",
   "uids": {
      "auto": "55ca9e43-e8de-4da7-bde8-ab0de1ece93a"
   },
   "volume_fraction": null
}