{
   "absolute_quantity": null,
   "file_links": [],
   "labels": [],
   "mass_fraction": null,
   "material": {
      "id": "3243b108-f9d8-428e-93c9-1d1199ff1cea",
      "scope": "auto",
      "type": "link_by_uid"
   },
   "name": "Composition AAB12 Ing.",
   "notes": null,
   "number_fraction": null,
   "process": {
      "id": "d5093105-0493-4634-a018-0f2d820980ee",
      "scope": "auto",
      "type": "link_by_uid"
   },
   "spec": {
      "id": "aebfc49f-2582-468c-a625-48272a632d37",
      "scope": "auto",
      "type": "link_by_uid"
   },
   "tags": [],
   "type": "ingredient_run",
   "uids": {
      "auto": "b6bb09e8-b227-4098-b940-b97a52199525"
   },
   "volume_fraction": null
}