{
   "absolute_quantity": null,
   "file_links": [],
   "labels": [],
   "mass_fraction": null,
   "material": {
      "id": "0371a95b-4f87-4d78-b6db-c0a928f7c570",
      "scope": "auto",
      "type": "link_by_uid"
   },
   "name": "Composition AAB14 Ing.",
   "notes": null,
   "number_fraction": null,
   "process": {
      "id": "ecb6c782-d7c5-4401-85d9-3d2bdd246b8c",
      "scope": "auto",
      "type": "link_by_uid"
   },
   "spec": {
      "id": "11c1890a-ce5b-46de-8a04-eb584ba8ead5",
      "scope": "auto",
      "type": "link_by_uid"
   },
   "tags": [],
   "type": "ingredient_run",
   "uids": {
      "auto": "c5883fe9-71dc-41fb-ad49-553381ec0cc7"
   },
   "volume_fraction": null
}