{
   "file_links": [],
   "name": "Alloy (AAB02-VAM-A): T. Sample (NI, T04)",
   "notes": null,
   "process": {
      "id": "28b02be0-f55d-47e7-b208-71bce40ed47f",
      "scope": "auto",
      "type": "link_by_uid"
   },
   "sample_type": null,
   "spec": {
      "id": "1056e425-f596-4b39-9527-700e325082de",
      "scope": "auto",
      "type": "link_by_uid"
   },
   "tags": [
      "composition_id::AAB02",
      "batch::A",
      "fabrication_method::VAM"
   ],
   "type": "material_run",
   "uids": {
      "auto": "294621a6-c996-4333-b32a-5c86716b6397"
   }
}