{
   "file_links": [],
   "name": "Alloy (AAB06-VAM-A): T. Sample (XRD, T03)",
   "notes": null,
   "process": {
      "id": "1ccb9d12-2e7f-481a-ab0e-0d78e75fcff6",
      "scope": "auto",
      "type": "link_by_uid"
   },
   "sample_type": null,
   "spec": {
      "id": "ca82bcd1-0b1c-49bc-8272-783133fd894b",
      "scope": "auto",
      "type": "link_by_uid"
   },
   "tags": [
      "composition_id::AAB06",
      "batch::A",
      "fabrication_method::VAM"
   ],
   "type": "material_run",
   "uids": {
      "auto": "536b657a-70e8-406c-a13d-d024250a7c4a"
   }
}