{
   "conditions": [],
   "file_links": [],
   "material": {
      "id": "e2f0343b-bd79-440a-96c6-73ca53587b3e",
      "scope": "auto",
      "type": "link_by_uid"
   },
   "name": "XRD charact. for Alloy (AAB16-VAM-A) (T03)",
   "notes": null,
   "parameters": [],
   "properties": [
      {
         "file_links": [],
         "name": "Phase",
         "notes": "",
         "origin": "measured",
         "template": null,
         "type": "property",
         "value": {
            "category": "L12",
            "type": "nominal_categorical"
         }
      },
      {
         "file_links": [],
         "name": "Lattice Parameter",
         "notes": "",
         "origin": "measured",
         "template": null,
         "type": "property",
         "value": {
            "nominal": 3.5707897317083104,
            "type": "nominal_real",
            "units": "centimeter"
         }
      },
      {
         "file_links": [],
         "name": "Hardness, HV",
         "notes": "",
         "origin": "measured",
         "template": null,
         "type": "property",
         "value": {
            "nominal": 229.35999999999999,
            "type": "nominal_real",
            "units": "pascal"
         }
      },
      {
         "file_links": [],
         "name": "SD, HV",
         "notes": "",
         "origin": "measured",
         "template": null,
         "type": "property",
         "value": {
            "nominal": 8.06244379825373,
            "type": "nominal_real",
            "units": "pascal"
         }
      }
   ],
   "source": null,
   "spec": {
      "id": "5dab630e-aab4-44de-be43-2870c282b312",
      "scope": "auto",
      "type": "link_by_uid"
   },
   "tags": [
      "composition_id::AAB16",
      "batch::A",
      "fabrication_method::VAM"
   ],
   "type": "measurement_run",
   "uids": {
      "auto": "2b0036e1-20fa-4a7d-95d4-bb53f9b25361"
   }
}