{
   "absolute_quantity": null,
   "file_links": [],
   "labels": [],
   "mass_fraction": null,
   "material": {
      "id": "04652550-4d9b-4bd5-b6ae-8af7ccae91e1",
      "scope": "auto",
      "type": "link_by_uid"
   },
   "name": "Forged Alloy (AAB01-VAM-A) Ing.",
   "notes": null,
   "number_fraction": null,
   "process": {
      "id": "cdcf20ef-357d-4267-b5d5-010647600bea",
      "scope": "auto",
      "type": "link_by_uid"
   },
   "tags": [],
   "type": "ingredient_spec",
   "uids": {
      "auto": "b9b4dd8c-3227-4671-9680-083d684f942f"
   },
   "volume_fraction": null
}