{
   "description": "Individual ingredient of a composition",
   "name": "Element",
   "properties": [
      [
         {
            "id": "9b39c478-e822-4293-a837-f7e97d16fba7",
            "scope": "auto",
            "type": "link_by_uid"
         },
         null
      ],
      [
         {
            "id": "bad88581-999f-41a3-a5ed-5dac84add9e5",
            "scope": "auto",
            "type": "link_by_uid"
         },
         null
      ]
   ],
   "tags": [],
   "type": "material_template",
   "uids": {
      "auto": "0fb87d5c-2459-4820-98d3-0343359af765",
      "persistent_id": 4
   }
}