{
   "absolute_quantity": null,
   "file_links": [],
   "labels": [],
   "mass_fraction": null,
   "material": {
      "id": "99e0e31c-bf1c-47c7-a9f4-6dd27b30df5c",
      "scope": "auto",
      "type": "link_by_uid"
   },
   "name": "Inferred Alloy Compositions Ing.",
   "notes": null,
   "number_fraction": null,
   "process": {
      "id": "58e746f1-0501-4131-b7b2-8ebdb2331ffc",
      "scope": "auto",
      "type": "link_by_uid"
   },
   "spec": {
      "id": "30fffed6-cad1-427d-99ba-fac54fbde28b",
      "scope": "auto",
      "type": "link_by_uid"
   },
   "tags": [],
   "type": "ingredient_run",
   "uids": {
      "auto": "c154a4e7-2071-4c98-89a5-af36ef7f2591"
   },
   "volume_fraction": null
}