{
   "absolute_quantity": null,
   "file_links": [],
   "labels": [],
   "mass_fraction": null,
   "material": {
      "id": "39c65e72-89fa-4717-82e1-4cf5880081ae",
      "scope": "auto",
      "type": "link_by_uid"
   },
   "name": "Alloy (AAB16-VAM-A): Traveler Ing.",
   "notes": null,
   "number_fraction": null,
   "process": {
      "id": "ca437580-8dd8-4087-97cd-2425c6040374",
      "scope": "auto",
      "type": "link_by_uid"
   },
   "spec": {
      "id": "9ac6a324-643e-41c4-81e1-2274cd38f8da",
      "scope": "auto",
      "type": "link_by_uid"
   },
   "tags": [],
   "type": "ingredient_run",
   "uids": {
      "auto": "c88cb799-417e-42f1-8854-1857d3493bcb"
   },
   "volume_fraction": null
}