{
   "absolute_quantity": null,
   "file_links": [],
   "labels": [],
   "mass_fraction": null,
   "material": {
      "id": "afdf7625-d108-4ff7-8823-1cf27922ed3c",
      "scope": "auto",
      "type": "link_by_uid"
   },
   "name": "Alloy (AAB05-VAM-A): T. Sample (Tensile, T08) Ing.",
   "notes": null,
   "number_fraction": null,
   "process": {
      "id": "66bb7c30-8a8b-430e-a87f-17ec042f91c1",
      "scope": "auto",
      "type": "link_by_uid"
   },
   "spec": {
      "id": "858d072d-51de-4305-85f8-8133acccc833",
      "scope": "auto",
      "type": "link_by_uid"
   },
   "tags": [],
   "type": "ingredient_run",
   "uids": {
      "auto": "178d8b25-d8d7-4bc6-a236-224aca22cbad"
   },
   "volume_fraction": null
}