{
   "absolute_quantity": null,
   "file_links": [],
   "labels": [],
   "mass_fraction": null,
   "material": {
      "id": "5ff41364-4c82-47cc-95c2-a949195941a4",
      "scope": "auto",
      "type": "link_by_uid"
   },
   "name": "Alloy (AAB15-VAM-A): T. Sample (NI, T04) Ing.",
   "notes": null,
   "number_fraction": null,
   "process": {
      "id": "ab284305-fb29-4b4d-8b0b-e0b1681ccaf5",
      "scope": "auto",
      "type": "link_by_uid"
   },
   "spec": {
      "id": "28fe0de8-456c-4050-b074-ad2afd559b41",
      "scope": "auto",
      "type": "link_by_uid"
   },
   "tags": [],
   "type": "ingredient_run",
   "uids": {
      "auto": "7eaee52a-335a-4135-8030-9c7fee324d8e"
   },
   "volume_fraction": null
}