{
   "absolute_quantity": null,
   "file_links": [],
   "labels": [],
   "mass_fraction": null,
   "material": {
      "id": "4400fc0e-c8a8-4344-bde8-d771bcf78cd4",
      "scope": "auto",
      "type": "link_by_uid"
   },
   "name": "Alloy (AAB10-VAM-A): T. Sample (SEM, T02) Ing.",
   "notes": null,
   "number_fraction": null,
   "process": {
      "id": "e6d9a196-fdd5-457c-8657-bddf9916fc89",
      "scope": "auto",
      "type": "link_by_uid"
   },
   "tags": [],
   "type": "ingredient_spec",
   "uids": {
      "auto": "82eadfe9-30b4-4c99-b8f8-fd52ac05cac7"
   },
   "volume_fraction": null
}