{
   "absolute_quantity": null,
   "file_links": [],
   "labels": [],
   "mass_fraction": null,
   "material": {
      "id": "4633d67d-b00f-4f0e-9b25-6e5fa7224ee6",
      "scope": "auto",
      "type": "link_by_uid"
   },
   "name": "Alloy (AAB02-VAM-A): T. Sample (Tensile, T09) Ing.",
   "notes": null,
   "number_fraction": null,
   "process": {
      "id": "66bb7c30-8a8b-430e-a87f-17ec042f91c1",
      "scope": "auto",
      "type": "link_by_uid"
   },
   "spec": {
      "id": "d8e1fb53-75e6-4af0-8eab-91a615b39617",
      "scope": "auto",
      "type": "link_by_uid"
   },
   "tags": [],
   "type": "ingredient_run",
   "uids": {
      "auto": "962bb43e-8d22-45c7-af7c-fcee6f0a3113"
   },
   "volume_fraction": null
}