{
   "absolute_quantity": null,
   "file_links": [],
   "labels": [],
   "mass_fraction": null,
   "material": {
      "id": "ee22dcc6-55ac-41af-914b-bc0a00a6be63",
      "scope": "auto",
      "type": "link_by_uid"
   },
   "name": "Alloy (AAB04-VAM-A): Traveler Ing.",
   "notes": null,
   "number_fraction": null,
   "process": {
      "id": "419bd271-f088-491b-8e83-6370c211cf09",
      "scope": "auto",
      "type": "link_by_uid"
   },
   "tags": [],
   "type": "ingredient_spec",
   "uids": {
      "auto": "4a8eab68-2b61-4e2e-9e84-0286d87694fd"
   },
   "volume_fraction": null
}