{
   "absolute_quantity": null,
   "file_links": [],
   "labels": [],
   "mass_fraction": null,
   "material": {
      "id": "ee22dcc6-55ac-41af-914b-bc0a00a6be63",
      "scope": "auto",
      "type": "link_by_uid"
   },
   "name": "Alloy (AAB04-VAM-A): Traveler Ing.",
   "notes": null,
   "number_fraction": null,
   "process": {
      "id": "fbfe5274-9017-49a7-af94-8b2d7975e0a1",
      "scope": "auto",
      "type": "link_by_uid"
   },
   "tags": [],
   "type": "ingredient_spec",
   "uids": {
      "auto": "e5448a4a-6628-4565-9e7b-5b7292f9b607"
   },
   "volume_fraction": null
}