{
   "conditions": [],
   "file_links": [],
   "material": {
      "id": "0af65e7f-8898-4ba6-8049-f4deb0820591",
      "scope": "auto",
      "type": "link_by_uid"
   },
   "name": "Weigh V for AAB04",
   "notes": null,
   "parameters": [],
   "properties": [
      {
         "file_links": [],
         "name": "Weighed Mass",
         "notes": null,
         "origin": "unknown",
         "template": null,
         "type": "property",
         "value": {
            "nominal": 1.3429,
            "type": "nominal_real",
            "units": "gram"
         }
      },
      {
         "file_links": [],
         "name": "Mass Loss",
         "notes": null,
         "origin": "specified",
         "template": {
            "id": "3ff37629-2103-48e3-8dbb-365421e0ed08",
            "scope": "auto",
            "type": "link_by_uid"
         },
         "type": "property",
         "value": {
            "nominal": 0.0,
            "type": "nominal_real",
            "units": "gram"
         }
      }
   ],
   "source": {
      "performed_by": "Wenle & Daniel",
      "performed_date": "2022-11-04",
      "type": "performed_source"
   },
   "spec": {
      "id": "8e6f2302-0647-4fc4-8c87-605d56914813",
      "scope": "auto",
      "type": "link_by_uid"
   },
   "tags": [
      "composition_id::AAB04",
      "batch::A",
      "fabrication_method::VAM"
   ],
   "type": "measurement_run",
   "uids": {
      "auto": "24516a20-5e65-41ac-bde1-072cd9057cd2"
   }
}