{
   "absolute_quantity": null,
   "file_links": [],
   "labels": [],
   "mass_fraction": null,
   "material": {
      "id": "eef6c9d3-06b3-4632-9101-0bbcb9b80271",
      "scope": "auto",
      "type": "link_by_uid"
   },
   "name": "Composition AAB15 Ing.",
   "notes": null,
   "number_fraction": null,
   "process": {
      "id": "ba07fcd0-3903-45cb-9ac1-0e56a4b57498",
      "scope": "auto",
      "type": "link_by_uid"
   },
   "tags": [],
   "type": "ingredient_spec",
   "uids": {
      "auto": "fb901b11-5d27-49a2-a824-03a862dfd10d"
   },
   "volume_fraction": null
}